[{"Name":"warschauer_strasse","key":"warschauer_strasse","name":"Warschauer Straße","dist_m":0},{"Name":"schlesisches_tor","key":"schlesisches_tor","name":"Schlesisches Tor","dist_m":799.36},{"Name":"goerlitzer_bahnhof","key":"goerlitzer_bahnhof","name":"Görlitzer Bahnhof","dist_m":1748.54},{"Name":"kottbusser_tor","key":"kottbusser_tor","name":"Kottbusser Tor","dist_m":2398.08},{"Name":"prinzenstrasse","key":"prinzenstrasse","name":"Prinzenstraße","dist_m":3276.26},{"Name":"hallesches_tor","key":"hallesches_tor","name":"Hallesches Tor","dist_m":4301.7},{"Name":"moeckernbruecke","key":"moeckernbruecke","name":"Möckernbrücke","dist_m":4839.69},{"Name":"gleisdreieck","key":"gleisdreieck","name":"Gleisdreieck","dist_m":5455.57},{"Name":"kurfuerstenstrasse","key":"kurfuerstenstrasse","name":"Kurfürstenstraße","dist_m":6332.17},{"Name":"nollendorfplatz","key":"nollendorfplatz","name":"Nollendorfplatz","dist_m":6807.82},{"Name":"wittenbergplatz","key":"wittenbergplatz","name":"Wittenbergplatz","dist_m":7682.63},{"Name":"kurfuerstendamm","key":"kurfuerstendamm","name":"Kurfürstendamm","dist_m":8542.71},{"Name":"uhlandstrasse","key":"uhlandstrasse","name":"Uhlandstraße","dist_m":8897.71}]